brutelib/__init__.py
brutelib/env/hashlist.txt
brutelib/env/wordlist.txt
brutelib-0.3.1.dist-info/METADATA
brutelib-0.3.1.dist-info/WHEEL
brutelib-0.3.1.dist-info/RECORD
