Metadata-Version: 2.1
Name: brutelib
Version: 0.3.1
Summary: Used for bruteforce examples ( EDUCATIONAL ) 
Author: CaiqueONz
Author-email: caiqueonz777@gmail.com
Requires-Python: >=3.8,<4.0
Classifier: Programming Language :: Python :: 3
Classifier: Programming Language :: Python :: 3.8
Classifier: Programming Language :: Python :: 3.9
Classifier: Programming Language :: Python :: 3.10
Classifier: Programming Language :: Python :: 3.11
